{
  "type": "supermartijn642corelib:conditional",
  "conditions": [
    {
      "block": "abstoneedition:smooth_black_marble_wall",
      "type": "abstoneedition:block_enabled"
    },
    {
      "block": "abstoneedition:smooth_black_marble",
      "type": "abstoneedition:block_enabled"
    }
  ],
  "recipe": {
    "type": "minecraft:stonecutting",
    "ingredient": {
      "item": "abstoneedition:smooth_black_marble"
    },
    "result": "abstoneedition:smooth_black_marble_wall",
    "count": 1
  }
}